hermes/__init__.py
hermes/__main__.py
hermes/commands/__init__.py
hermes/commands/base.py
hermes/commands/clean/__init__.py
hermes/commands/clean/base.py
hermes/commands/cli.py
hermes/commands/curate/__init__.py
hermes/commands/curate/base.py
hermes/commands/deposit/__init__.py
hermes/commands/deposit/base.py
hermes/commands/deposit/error.py
hermes/commands/deposit/file.py
hermes/commands/deposit/invenio.py
hermes/commands/deposit/invenio_rdm.py
hermes/commands/deposit/rodare.py
hermes/commands/harvest/__init__.py
hermes/commands/harvest/base.py
hermes/commands/harvest/cff.py
hermes/commands/harvest/codemeta.py
hermes/commands/harvest/util/__init__.py
hermes/commands/harvest/util/validate_codemeta.py
hermes/commands/init/__init__.py
hermes/commands/init/base.py
hermes/commands/init/util/__init__.py
hermes/commands/init/util/connect_github.py
hermes/commands/init/util/connect_gitlab.py
hermes/commands/init/util/connect_zenodo.py
hermes/commands/init/util/oauth_process.py
hermes/commands/init/util/slim_click.py
hermes/commands/marketplace.py
hermes/commands/postprocess/__init__.py
hermes/commands/postprocess/base.py
hermes/commands/postprocess/invenio.py
hermes/commands/postprocess/invenio_rdm.py
hermes/commands/process/__init__.py
hermes/commands/process/base.py
hermes/error.py
hermes/logger.py
hermes/model/__init__.py
hermes/model/context.py
hermes/model/errors.py
hermes/model/merge.py
hermes/model/path.py
hermes/utils.py
hermes-0.9.0.dist-info/LICENSE.md
hermes-0.9.0.dist-info/LICENSES/Apache-2.0.txt
hermes-0.9.0.dist-info/LICENSES/CC-BY-ND-4.0.txt
hermes-0.9.0.dist-info/LICENSES/CC-BY-SA-4.0.txt
hermes-0.9.0.dist-info/LICENSES/CC0-1.0.txt
hermes-0.9.0.dist-info/LICENSES/LicenseRef-BSD-Caltech.txt
hermes-0.9.0.dist-info/METADATA
hermes-0.9.0.dist-info/WHEEL
hermes-0.9.0.dist-info/entry_points.txt
hermes-0.9.0.dist-info/RECORD
