Metadata-Version: 2.3
Name: hermes
Version: 0.9.0
Summary: Workflow to publish research software with rich metadata
License: Apache-2.0
Keywords: publishing,metadata,automation
Author: Oliver Bertuch
Author-email: o.bertuch@fz-juelich.de
Requires-Python: >=3.10,<4.0
Classifier: License :: OSI Approved :: Apache Software License
Classifier: Programming Language :: Python :: 3
Classifier: Programming Language :: Python :: 3.10
Classifier: Programming Language :: Python :: 3.11
Classifier: Programming Language :: Python :: 3.12
Classifier: Programming Language :: Python :: 3.13
Requires-Dist: cffconvert (>=2.0.0,<3.0.0)
Requires-Dist: jsonschema (>=3.0.0,<4.0.0)
Requires-Dist: pydantic (>=2.5.1,<3.0.0)
Requires-Dist: pydantic-settings (>=2.1.0,<3.0.0)
Requires-Dist: pyld (>=2.0.3,<3.0.0)
Requires-Dist: pynacl (>=1.5.0,<2.0.0)
Requires-Dist: pyparsing (>=3.0.9,<4.0.0)
Requires-Dist: requests (>=2.28.1,<3.0.0)
Requires-Dist: requests-oauthlib (>=2.0.0,<3.0.0)
Requires-Dist: ruamel.yaml (>=0.17.21,<0.18.0)
Requires-Dist: toml (>=0.10.2,<0.11.0)
Project-URL: Documentation, https://hermes.software-metadata.pub
Project-URL: Homepage, https://software-metadata.pub
Project-URL: Repository, https://github.com/softwarepub/hermes
